[
  {
    "epoch": 1,
    "matrix_f1": 0.0,
    "matrix_precision": 0.0,
    "matrix_recall": 0.0,
    "dimension_seq_f1": 1,
    "sentiment_seq_f1": 1,
    "score": 0.0,
    "train_loss": 60.81030730808097,
    "val_loss": 7.152642049789429,
    "epoch_time": 139.66216611862183,
    "val_loss_va": 3.526877554655075,
    "train_loss_va": 4.788145109323805
  },
  {
    "epoch": 2,
    "matrix_f1": 0.0,
    "matrix_precision": 0.0,
    "matrix_recall": 0.0,
    "dimension_seq_f1": 1,
    "sentiment_seq_f1": 1,
    "score": 0.0,
    "train_loss": 5.5198838558702406,
    "val_loss": 4.24442889213562,
    "epoch_time": 138.65529561042786,
    "val_loss_va": 1.5638685566186905,
    "train_loss_va": 2.0571684633930953
  },
  {
    "epoch": 3,
    "matrix_f1": 0.0,
    "matrix_precision": 0.0,
    "matrix_recall": 0.0,
    "dimension_seq_f1": 1,
    "sentiment_seq_f1": 1,
    "score": 0.0,
    "train_loss": 3.8816225208173907,
    "val_loss": 4.043772082328797,
    "epoch_time": 138.3884778022766,
    "val_loss_va": 1.3969478404521942,
    "train_loss_va": 1.0851830769553268
  },
  {
    "epoch": 4,
    "matrix_f1": 0.0125,
    "matrix_precision": 0.6666666666666666,
    "matrix_recall": 0.006309148264984227,
    "dimension_seq_f1": 1,
    "sentiment_seq_f1": 1,
    "score": 0.0125,
    "train_loss": 3.533841134170555,
    "val_loss": 3.916790487766266,
    "epoch_time": 138.3201961517334,
    "val_loss_va": 1.1311714029312134,
    "train_loss_va": 0.9261345686253902
  },
  {
    "epoch": 5,
    "matrix_f1": 0.036923076923076927,
    "matrix_precision": 0.75,
    "matrix_recall": 0.01892744479495268,
    "dimension_seq_f1": 1,
    "sentiment_seq_f1": 1,
    "score": 0.036923076923076927,
    "train_loss": 3.3012025607813795,
    "val_loss": 3.9644874572753905,
    "epoch_time": 138.29011392593384,
    "val_loss_va": 1.200982301235199,
    "train_loss_va": 0.8560722919073143
  },
  {
    "epoch": 6,
    "matrix_f1": 0.031055900621118012,
    "matrix_precision": 1.0,
    "matrix_recall": 0.015772870662460567,
    "dimension_seq_f1": 1,
    "sentiment_seq_f1": 1,
    "score": 0.031055900621118012,
    "train_loss": 3.098559647827785,
    "val_loss": 3.980148205757141,
    "epoch_time": 138.14805555343628,
    "val_loss_va": 1.1757553404569625,
    "train_loss_va": 0.7901136692617019
  },
  {
    "epoch": 7,
    "matrix_f1": 0.030581039755351678,
    "matrix_precision": 0.5,
    "matrix_recall": 0.015772870662460567,
    "dimension_seq_f1": 1,
    "sentiment_seq_f1": 1,
    "score": 0.030581039755351678,
    "train_loss": 2.9244757826358696,
    "val_loss": 3.99285698890686,
    "epoch_time": 138.25332856178284,
    "val_loss_va": 1.1663281643390655,
    "train_loss_va": 0.735136181741251
  },
  {
    "epoch": 8,
    "matrix_f1": 0.12068965517241378,
    "matrix_precision": 0.6774193548387096,
    "matrix_recall": 0.06624605678233439,
    "dimension_seq_f1": 1,
    "sentiment_seq_f1": 1,
    "score": 0.12068965517241378,
    "train_loss": 2.771037318287701,
    "val_loss": 4.012522871494293,
    "epoch_time": 138.21928596496582,
    "val_loss_va": 1.13984121799469,
    "train_loss_va": 0.7147790087465566
  },
  {
    "epoch": 9,
    "matrix_f1": 0.10029498525073746,
    "matrix_precision": 0.7727272727272727,
    "matrix_recall": 0.05362776025236593,
    "dimension_seq_f1": 1,
    "sentiment_seq_f1": 1,
    "score": 0.10029498525073746,
    "train_loss": 2.6370096302594006,
    "val_loss": 4.132728526592254,
    "epoch_time": 138.60730862617493,
    "val_loss_va": 1.101112231016159,
    "train_loss_va": 0.6657482619900933
  },
  {
    "epoch": 10,
    "matrix_f1": 0.10951008645533143,
    "matrix_precision": 0.6333333333333333,
    "matrix_recall": 0.05993690851735016,
    "dimension_seq_f1": 1,
    "sentiment_seq_f1": 1,
    "score": 0.10951008645533143,
    "train_loss": 2.5145322716154226,
    "val_loss": 4.420346858501435,
    "epoch_time": 138.65659141540527,
    "val_loss_va": 1.1016636538505553,
    "train_loss_va": 0.6437278091322568
  },
  {
    "epoch": 11,
    "matrix_f1": 0.17934782608695654,
    "matrix_precision": 0.6470588235294118,
    "matrix_recall": 0.10410094637223975,
    "dimension_seq_f1": 1,
    "sentiment_seq_f1": 1,
    "score": 0.17934782608695654,
    "train_loss": 2.397959201387381,
    "val_loss": 4.069289941787719,
    "epoch_time": 138.28569769859314,
    "val_loss_va": 1.0217600056529046,
    "train_loss_va": 0.6115297873022805
  },
  {
    "epoch": 12,
    "matrix_f1": 0.24352331606217617,
    "matrix_precision": 0.6811594202898551,
    "matrix_recall": 0.14826498422712933,
    "dimension_seq_f1": 1,
    "sentiment_seq_f1": 1,
    "score": 0.24352331606217617,
    "train_loss": 2.2960174608394373,
    "val_loss": 4.155516839027404,
    "epoch_time": 138.33241820335388,
    "val_loss_va": 1.1121556848287582,
    "train_loss_va": 0.5773104605090396
  },
  {
    "epoch": 13,
    "matrix_f1": 0.25692695214105793,
    "matrix_precision": 0.6375,
    "matrix_recall": 0.1608832807570978,
    "dimension_seq_f1": 1,
    "sentiment_seq_f1": 1,
    "score": 0.25692695214105793,
    "train_loss": 2.189183484993224,
    "val_loss": 4.4964967179298405,
    "epoch_time": 138.7908012866974,
    "val_loss_va": 1.0958522537350655,
    "train_loss_va": 0.5256720318260646
  },
  {
    "epoch": 14,
    "matrix_f1": 0.25575447570332477,
    "matrix_precision": 0.6756756756756757,
    "matrix_recall": 0.15772870662460567,
    "dimension_seq_f1": 1,
    "sentiment_seq_f1": 1,
    "score": 0.25575447570332477,
    "train_loss": 2.1053568855937024,
    "val_loss": 4.361218614578247,
    "epoch_time": 138.19262623786926,
    "val_loss_va": 1.0350593107938766,
    "train_loss_va": 0.5012250395127964
  },
  {
    "epoch": 15,
    "matrix_f1": 0.2643391521197007,
    "matrix_precision": 0.6309523809523809,
    "matrix_recall": 0.167192429022082,
    "dimension_seq_f1": 1,
    "sentiment_seq_f1": 1,
    "score": 0.2643391521197007,
    "train_loss": 2.025814715176967,
    "val_loss": 4.5718233370780945,
    "epoch_time": 138.13068771362305,
    "val_loss_va": 1.1077107745409012,
    "train_loss_va": 0.47990288055877517
  },
  {
    "epoch": 16,
    "matrix_f1": 0.2538860103626943,
    "matrix_precision": 0.7101449275362319,
    "matrix_recall": 0.15457413249211358,
    "dimension_seq_f1": 1,
    "sentiment_seq_f1": 1,
    "score": 0.2538860103626943,
    "train_loss": 1.9529731217790047,
    "val_loss": 4.659678907394409,
    "epoch_time": 137.46112251281738,
    "val_loss_va": 1.0988146877288818,
    "train_loss_va": 0.44640702934491505
  },
  {
    "epoch": 17,
    "matrix_f1": 0.2800982800982801,
    "matrix_precision": 0.6333333333333333,
    "matrix_recall": 0.17981072555205047,
    "dimension_seq_f1": 1,
    "sentiment_seq_f1": 1,
    "score": 0.2800982800982801,
    "train_loss": 1.877489722453577,
    "val_loss": 5.076530160903931,
    "epoch_time": 137.16512274742126,
    "val_loss_va": 1.194398278594017,
    "train_loss_va": 0.4273732208424742
  },
  {
    "epoch": 18,
    "matrix_f1": 0.25906735751295334,
    "matrix_precision": 0.7246376811594203,
    "matrix_recall": 0.15772870662460567,
    "dimension_seq_f1": 1,
    "sentiment_seq_f1": 1,
    "score": 0.25906735751295334,
    "train_loss": 1.8255185748983296,
    "val_loss": 5.022101829051971,
    "epoch_time": 136.8732693195343,
    "val_loss_va": 1.226317946910858,
    "train_loss_va": 0.4065124422523821
  },
  {
    "epoch": 19,
    "matrix_f1": 0.25906735751295334,
    "matrix_precision": 0.7246376811594203,
    "matrix_recall": 0.15772870662460567,
    "dimension_seq_f1": 1,
    "sentiment_seq_f1": 1,
    "score": 0.25906735751295334,
    "train_loss": 1.7592128848362718,
    "val_loss": 5.131167199611664,
    "epoch_time": 136.80890727043152,
    "val_loss_va": 1.229973330795765,
    "train_loss_va": 0.3833185816558409
  },
  {
    "epoch": 20,
    "matrix_f1": 0.2727272727272727,
    "matrix_precision": 0.6835443037974683,
    "matrix_recall": 0.17034700315457413,
    "dimension_seq_f1": 1,
    "sentiment_seq_f1": 1,
    "score": 0.2727272727272727,
    "train_loss": 1.7050010690335788,
    "val_loss": 5.2075146651268005,
    "epoch_time": 136.8558759689331,
    "val_loss_va": 1.1830492877960206,
    "train_loss_va": 0.36446088443165675
  },
  {
    "epoch": 21,
    "matrix_f1": 0.2570694087403599,
    "matrix_precision": 0.6944444444444444,
    "matrix_recall": 0.15772870662460567,
    "dimension_seq_f1": 1,
    "sentiment_seq_f1": 1,
    "score": 0.2570694087403599,
    "train_loss": 1.6519352855988878,
    "val_loss": 5.464784464836121,
    "epoch_time": 136.76143503189087,
    "val_loss_va": 1.1201690554618835,
    "train_loss_va": 0.3402637228099181
  },
  {
    "epoch": 22,
    "matrix_f1": 0.271356783919598,
    "matrix_precision": 0.6666666666666666,
    "matrix_recall": 0.17034700315457413,
    "dimension_seq_f1": 1,
    "sentiment_seq_f1": 1,
    "score": 0.271356783919598,
    "train_loss": 1.613040307523926,
    "val_loss": 5.447480406761169,
    "epoch_time": 136.61850690841675,
    "val_loss_va": 1.2258468300104142,
    "train_loss_va": 0.34156960057564467
  },
  {
    "epoch": 23,
    "matrix_f1": 0.2673521850899743,
    "matrix_precision": 0.7222222222222222,
    "matrix_recall": 0.1640378548895899,
    "dimension_seq_f1": 1,
    "sentiment_seq_f1": 1,
    "score": 0.2673521850899743,
    "train_loss": 1.5603825210998523,
    "val_loss": 5.455273616313934,
    "epoch_time": 136.72153615951538,
    "val_loss_va": 1.1860200649499892,
    "train_loss_va": 0.31193150055317814
  },
  {
    "epoch": 24,
    "matrix_f1": 0.2690355329949239,
    "matrix_precision": 0.6883116883116883,
    "matrix_recall": 0.167192429022082,
    "dimension_seq_f1": 1,
    "sentiment_seq_f1": 1,
    "score": 0.2690355329949239,
    "train_loss": 1.519786929315042,
    "val_loss": 5.603037662506104,
    "epoch_time": 136.56197047233582,
    "val_loss_va": 1.2219575923681258,
    "train_loss_va": 0.31175198446926355
  },
  {
    "epoch": 25,
    "matrix_f1": 0.27930174563591026,
    "matrix_precision": 0.6666666666666666,
    "matrix_recall": 0.17665615141955837,
    "dimension_seq_f1": 1,
    "sentiment_seq_f1": 1,
    "score": 0.27930174563591026,
    "train_loss": 1.4866559255696372,
    "val_loss": 5.59930849313736,
    "epoch_time": 136.77429485321045,
    "val_loss_va": 1.2445851147174836,
    "train_loss_va": 0.30050999984525373
  },
  {
    "epoch": 26,
    "matrix_f1": 0.2762148337595908,
    "matrix_precision": 0.7297297297297297,
    "matrix_recall": 0.17034700315457413,
    "dimension_seq_f1": 1,
    "sentiment_seq_f1": 1,
    "score": 0.2762148337595908,
    "train_loss": 1.4475631425202886,
    "val_loss": 5.525297875404358,
    "epoch_time": 136.70823502540588,
    "val_loss_va": 1.1773140287399293,
    "train_loss_va": 0.2976138748976167
  },
  {
    "epoch": 27,
    "matrix_f1": 0.2800982800982801,
    "matrix_precision": 0.6333333333333333,
    "matrix_recall": 0.17981072555205047,
    "dimension_seq_f1": 1,
    "sentiment_seq_f1": 1,
    "score": 0.2800982800982801,
    "train_loss": 1.412100250224955,
    "val_loss": 5.937545368671417,
    "epoch_time": 136.73582673072815,
    "val_loss_va": 1.2245612865686417,
    "train_loss_va": 0.2795885268642665
  },
  {
    "epoch": 28,
    "matrix_f1": 0.27067669172932335,
    "matrix_precision": 0.6585365853658537,
    "matrix_recall": 0.17034700315457413,
    "dimension_seq_f1": 1,
    "sentiment_seq_f1": 1,
    "score": 0.27067669172932335,
    "train_loss": 1.3716727961969797,
    "val_loss": 5.699939548969269,
    "epoch_time": 136.68638467788696,
    "val_loss_va": 1.2023811721801758,
    "train_loss_va": 0.26858617559119224
  },
  {
    "epoch": 29,
    "matrix_f1": 0.26108374384236455,
    "matrix_precision": 0.5955056179775281,
    "matrix_recall": 0.167192429022082,
    "dimension_seq_f1": 1,
    "sentiment_seq_f1": 1,
    "score": 0.26108374384236455,
    "train_loss": 1.3381770545062888,
    "val_loss": 5.832137076854706,
    "epoch_time": 136.8718023300171,
    "val_loss_va": 1.1807895308732987,
    "train_loss_va": 0.2635802600744808
  },
  {
    "epoch": 30,
    "matrix_f1": 0.27184466019417475,
    "matrix_precision": 0.5894736842105263,
    "matrix_recall": 0.17665615141955837,
    "dimension_seq_f1": 1,
    "sentiment_seq_f1": 1,
    "score": 0.27184466019417475,
    "train_loss": 1.3061100440474558,
    "val_loss": 6.087591893672943,
    "epoch_time": 136.87685298919678,
    "val_loss_va": 1.1581075495481492,
    "train_loss_va": 0.2587022227075196
  },
  {
    "epoch": 31,
    "matrix_f1": 0.2457002457002457,
    "matrix_precision": 0.5555555555555556,
    "matrix_recall": 0.15772870662460567,
    "dimension_seq_f1": 1,
    "sentiment_seq_f1": 1,
    "score": 0.2457002457002457,
    "train_loss": 1.272907990015407,
    "val_loss": 5.994373970031738,
    "epoch_time": 136.67497611045837,
    "val_loss_va": 1.2421905064582826,
    "train_loss_va": 0.2511202710606633
  },
  {
    "epoch": 32,
    "matrix_f1": 0.26634382566585957,
    "matrix_precision": 0.5729166666666666,
    "matrix_recall": 0.17350157728706625,
    "dimension_seq_f1": 1,
    "sentiment_seq_f1": 1,
    "score": 0.26634382566585957,
    "train_loss": 1.2474260994976238,
    "val_loss": 6.099767758846283,
    "epoch_time": 137.14444732666016,
    "val_loss_va": 1.20809814453125,
    "train_loss_va": 0.25278491791341384
  },
  {
    "epoch": 33,
    "matrix_f1": 0.26252983293556087,
    "matrix_precision": 0.5392156862745098,
    "matrix_recall": 0.17350157728706625,
    "dimension_seq_f1": 1,
    "sentiment_seq_f1": 1,
    "score": 0.26252983293556087,
    "train_loss": 1.2196091141796674,
    "val_loss": 6.477154638767242,
    "epoch_time": 136.84072995185852,
    "val_loss_va": 1.2329327547550202,
    "train_loss_va": 0.24490137380329385
  },
  {
    "epoch": 34,
    "matrix_f1": 0.27188940092165903,
    "matrix_precision": 0.5042735042735043,
    "matrix_recall": 0.1861198738170347,
    "dimension_seq_f1": 1,
    "sentiment_seq_f1": 1,
    "score": 0.27188940092165903,
    "train_loss": 1.1873582217831373,
    "val_loss": 6.273569903373718,
    "epoch_time": 137.1944317817688,
    "val_loss_va": 1.210086343884468,
    "train_loss_va": 0.23678921052310486
  },
  {
    "epoch": 35,
    "matrix_f1": 0.2692307692307692,
    "matrix_precision": 0.5656565656565656,
    "matrix_recall": 0.17665615141955837,
    "dimension_seq_f1": 1,
    "sentiment_seq_f1": 1,
    "score": 0.2692307692307692,
    "train_loss": 1.1557303040166833,
    "val_loss": 6.940105910301209,
    "epoch_time": 137.5505986213684,
    "val_loss_va": 1.1954451453685762,
    "train_loss_va": 0.2271013195015
  },
  {
    "epoch": 36,
    "matrix_f1": 0.2576112412177986,
    "matrix_precision": 0.5,
    "matrix_recall": 0.17350157728706625,
    "dimension_seq_f1": 1,
    "sentiment_seq_f1": 1,
    "score": 0.2576112412177986,
    "train_loss": 1.1286773330388522,
    "val_loss": 6.6806346130371095,
    "epoch_time": 137.48014950752258,
    "val_loss_va": 1.2302357733249665,
    "train_loss_va": 0.22217705935035065
  },
  {
    "epoch": 37,
    "matrix_f1": 0.24941176470588233,
    "matrix_precision": 0.49074074074074076,
    "matrix_recall": 0.167192429022082,
    "dimension_seq_f1": 1,
    "sentiment_seq_f1": 1,
    "score": 0.24941176470588233,
    "train_loss": 1.1043499048371543,
    "val_loss": 6.65842087984085,
    "epoch_time": 137.5847613811493,
    "val_loss_va": 1.220531993508339,
    "train_loss_va": 0.2216128095128995
  },
  {
    "epoch": 38,
    "matrix_f1": 0.2429906542056075,
    "matrix_precision": 0.46846846846846846,
    "matrix_recall": 0.1640378548895899,
    "dimension_seq_f1": 1,
    "sentiment_seq_f1": 1,
    "score": 0.2429906542056075,
    "train_loss": 1.0798305447804681,
    "val_loss": 6.794329044818878,
    "epoch_time": 137.55750370025635,
    "val_loss_va": 1.1682308113574982,
    "train_loss_va": 0.21253041809898188
  },
  {
    "epoch": 39,
    "matrix_f1": 0.24824355971896953,
    "matrix_precision": 0.4818181818181818,
    "matrix_recall": 0.167192429022082,
    "dimension_seq_f1": 1,
    "sentiment_seq_f1": 1,
    "score": 0.24824355971896953,
    "train_loss": 1.0638378236636563,
    "val_loss": 6.774806396961212,
    "epoch_time": 137.32470989227295,
    "val_loss_va": 1.1698171705007554,
    "train_loss_va": 0.2158564421859176
  },
  {
    "epoch": 40,
    "matrix_f1": 0.2678571428571428,
    "matrix_precision": 0.4580152671755725,
    "matrix_recall": 0.1892744479495268,
    "dimension_seq_f1": 1,
    "sentiment_seq_f1": 1,
    "score": 0.2678571428571428,
    "train_loss": 1.0328829187874238,
    "val_loss": 6.8379397964477535,
    "epoch_time": 136.9682993888855,
    "val_loss_va": 1.2079354923963548,
    "train_loss_va": 0.20848862227450934
  },
  {
    "epoch": 41,
    "matrix_f1": 0.27292110874200426,
    "matrix_precision": 0.42105263157894735,
    "matrix_recall": 0.20189274447949526,
    "dimension_seq_f1": 1,
    "sentiment_seq_f1": 1,
    "score": 0.27292110874200426,
    "train_loss": 1.0114079787815402,
    "val_loss": 7.470012927055359,
    "epoch_time": 137.3998613357544,
    "val_loss_va": 1.2282420784235,
    "train_loss_va": 0.20047043051691296
  },
  {
    "epoch": 42,
    "matrix_f1": 0.27088036117381487,
    "matrix_precision": 0.47619047619047616,
    "matrix_recall": 0.1892744479495268,
    "dimension_seq_f1": 1,
    "sentiment_seq_f1": 1,
    "score": 0.27088036117381487,
    "train_loss": 0.9938700669998042,
    "val_loss": 7.277408854961395,
    "epoch_time": 137.51528072357178,
    "val_loss_va": 1.2858527356386185,
    "train_loss_va": 0.20596219769791427
  },
  {
    "epoch": 43,
    "matrix_f1": 0.2638888888888889,
    "matrix_precision": 0.4956521739130435,
    "matrix_recall": 0.17981072555205047,
    "dimension_seq_f1": 1,
    "sentiment_seq_f1": 1,
    "score": 0.2638888888888889,
    "train_loss": 0.9790039857862274,
    "val_loss": 7.2557316541671755,
    "epoch_time": 137.28313636779785,
    "val_loss_va": 1.303201504945755,
    "train_loss_va": 0.20108147094554477
  },
  {
    "epoch": 44,
    "matrix_f1": 0.2618510158013544,
    "matrix_precision": 0.4603174603174603,
    "matrix_recall": 0.1829652996845426,
    "dimension_seq_f1": 1,
    "sentiment_seq_f1": 1,
    "score": 0.2618510158013544,
    "train_loss": 0.9491011215203877,
    "val_loss": 7.189370365142822,
    "epoch_time": 137.46738243103027,
    "val_loss_va": 1.218980970978737,
    "train_loss_va": 0.1924065477383836
  },
  {
    "epoch": 45,
    "matrix_f1": 0.28054298642533937,
    "matrix_precision": 0.496,
    "matrix_recall": 0.19558359621451105,
    "dimension_seq_f1": 1,
    "sentiment_seq_f1": 1,
    "score": 0.28054298642533937,
    "train_loss": 0.9325683562777812,
    "val_loss": 7.487440552711487,
    "epoch_time": 137.66417407989502,
    "val_loss_va": 1.198783432841301,
    "train_loss_va": 0.18896697425777942
  },
  {
    "epoch": 46,
    "matrix_f1": 0.2522522522522523,
    "matrix_precision": 0.4409448818897638,
    "matrix_recall": 0.17665615141955837,
    "dimension_seq_f1": 1,
    "sentiment_seq_f1": 1,
    "score": 0.2522522522522523,
    "train_loss": 0.9191805890398475,
    "val_loss": 7.2861111760139465,
    "epoch_time": 137.96283793449402,
    "val_loss_va": 1.201670419573784,
    "train_loss_va": 0.1857570558018668
  },
  {
    "epoch": 47,
    "matrix_f1": 0.26905829596412556,
    "matrix_precision": 0.46511627906976744,
    "matrix_recall": 0.1892744479495268,
    "dimension_seq_f1": 1,
    "sentiment_seq_f1": 1,
    "score": 0.26905829596412556,
    "train_loss": 0.8986664617085013,
    "val_loss": 7.6895487070083615,
    "epoch_time": 138.29055190086365,
    "val_loss_va": 1.208975863456726,
    "train_loss_va": 0.18252224917683504
  },
  {
    "epoch": 48,
    "matrix_f1": 0.28953229398663693,
    "matrix_precision": 0.49242424242424243,
    "matrix_recall": 0.20504731861198738,
    "dimension_seq_f1": 1,
    "sentiment_seq_f1": 1,
    "score": 0.28953229398663693,
    "train_loss": 0.8798300773636516,
    "val_loss": 8.16589014530182,
    "epoch_time": 138.12151718139648,
    "val_loss_va": 1.2389839828014373,
    "train_loss_va": 0.18241439147745428
  },
  {
    "epoch": 49,
    "matrix_f1": 0.28193832599118945,
    "matrix_precision": 0.46715328467153283,
    "matrix_recall": 0.20189274447949526,
    "dimension_seq_f1": 1,
    "sentiment_seq_f1": 1,
    "score": 0.28193832599118945,
    "train_loss": 0.8558208726353804,
    "val_loss": 7.785022814273834,
    "epoch_time": 137.94665622711182,
    "val_loss_va": 1.3132300668954848,
    "train_loss_va": 0.17381983600333845
  },
  {
    "epoch": 50,
    "matrix_f1": 0.28820960698689957,
    "matrix_precision": 0.46808510638297873,
    "matrix_recall": 0.2082018927444795,
    "dimension_seq_f1": 1,
    "sentiment_seq_f1": 1,
    "score": 0.28820960698689957,
    "train_loss": 0.8478170849960498,
    "val_loss": 7.965617017745972,
    "epoch_time": 137.44543027877808,
    "val_loss_va": 1.2480377572774888,
    "train_loss_va": 0.1804316626848896
  },
  {
    "epoch": 51,
    "matrix_f1": 0.26666666666666666,
    "matrix_precision": 0.45112781954887216,
    "matrix_recall": 0.1892744479495268,
    "dimension_seq_f1": 1,
    "sentiment_seq_f1": 1,
    "score": 0.26666666666666666,
    "train_loss": 0.8290796430015588,
    "val_loss": 7.805688438415527,
    "epoch_time": 137.42927289009094,
    "val_loss_va": 1.2305416601896286,
    "train_loss_va": 0.17185261535025964
  },
  {
    "epoch": 52,
    "matrix_f1": 0.28633405639913234,
    "matrix_precision": 0.4583333333333333,
    "matrix_recall": 0.2082018927444795,
    "dimension_seq_f1": 1,
    "sentiment_seq_f1": 1,
    "score": 0.28633405639913234,
    "train_loss": 0.8130037955523005,
    "val_loss": 8.1666672205925,
    "epoch_time": 137.3603389263153,
    "val_loss_va": 1.240845964550972,
    "train_loss_va": 0.1716405132344912
  },
  {
    "epoch": 53,
    "matrix_f1": 0.2888888888888889,
    "matrix_precision": 0.48872180451127817,
    "matrix_recall": 0.20504731861198738,
    "dimension_seq_f1": 1,
    "sentiment_seq_f1": 1,
    "score": 0.2888888888888889,
    "train_loss": 0.8000132408398876,
    "val_loss": 8.010318827629089,
    "epoch_time": 137.94500613212585,
    "val_loss_va": 1.250789186358452,
    "train_loss_va": 0.1679860082682555
  },
  {
    "epoch": 54,
    "matrix_f1": 0.2894736842105263,
    "matrix_precision": 0.4748201438848921,
    "matrix_recall": 0.2082018927444795,
    "dimension_seq_f1": 1,
    "sentiment_seq_f1": 1,
    "score": 0.2894736842105263,
    "train_loss": 0.781706448099681,
    "val_loss": 8.093890304565429,
    "epoch_time": 137.38872623443604,
    "val_loss_va": 1.2006551271677017,
    "train_loss_va": 0.1624038876623822
  },
  {
    "epoch": 55,
    "matrix_f1": 0.28758169934640526,
    "matrix_precision": 0.4647887323943662,
    "matrix_recall": 0.2082018927444795,
    "dimension_seq_f1": 1,
    "sentiment_seq_f1": 1,
    "score": 0.28758169934640526,
    "train_loss": 0.7704078209777458,
    "val_loss": 8.087157337665557,
    "epoch_time": 137.56254816055298,
    "val_loss_va": 1.2335625618696213,
    "train_loss_va": 0.161823794779471
  },
  {
    "epoch": 56,
    "matrix_f1": 0.27937915742793795,
    "matrix_precision": 0.4701492537313433,
    "matrix_recall": 0.19873817034700317,
    "dimension_seq_f1": 1,
    "sentiment_seq_f1": 1,
    "score": 0.27937915742793795,
    "train_loss": 0.7572028000013751,
    "val_loss": 8.491413900852203,
    "epoch_time": 137.5628535747528,
    "val_loss_va": 1.2376915937662125,
    "train_loss_va": 0.15988958914699333
  },
  {
    "epoch": 57,
    "matrix_f1": 0.2942430703624734,
    "matrix_precision": 0.45394736842105265,
    "matrix_recall": 0.21766561514195584,
    "dimension_seq_f1": 1,
    "sentiment_seq_f1": 1,
    "score": 0.2942430703624734,
    "train_loss": 0.7392999414021882,
    "val_loss": 8.064405143260956,
    "epoch_time": 137.6617796421051,
    "val_loss_va": 1.2417280280590057,
    "train_loss_va": 0.16167215181293443
  },
  {
    "epoch": 58,
    "matrix_f1": 0.2972399150743099,
    "matrix_precision": 0.45454545454545453,
    "matrix_recall": 0.22082018927444794,
    "dimension_seq_f1": 1,
    "sentiment_seq_f1": 1,
    "score": 0.2972399150743099,
    "train_loss": 0.7270562295693177,
    "val_loss": 8.590683178901672,
    "epoch_time": 137.35769987106323,
    "val_loss_va": 1.2382157415151596,
    "train_loss_va": 0.1584552622229314
  },
  {
    "epoch": 59,
    "matrix_f1": 0.29473684210526313,
    "matrix_precision": 0.4430379746835443,
    "matrix_recall": 0.22082018927444794,
    "dimension_seq_f1": 1,
    "sentiment_seq_f1": 1,
    "score": 0.29473684210526313,
    "train_loss": 0.7186144622731899,
    "val_loss": 8.435233261585235,
    "epoch_time": 137.632554769516,
    "val_loss_va": 1.2647743231058122,
    "train_loss_va": 0.15814807016120985
  },
  {
    "epoch": 60,
    "matrix_f1": 0.28758169934640526,
    "matrix_precision": 0.4647887323943662,
    "matrix_recall": 0.2082018927444795,
    "dimension_seq_f1": 1,
    "sentiment_seq_f1": 1,
    "score": 0.28758169934640526,
    "train_loss": 0.7071360772269046,
    "val_loss": 8.881350424289703,
    "epoch_time": 137.24588227272034,
    "val_loss_va": 1.2660381764173507,
    "train_loss_va": 0.15479395876001564
  },
  {
    "epoch": 61,
    "matrix_f1": 0.2974137931034483,
    "matrix_precision": 0.46938775510204084,
    "matrix_recall": 0.21766561514195584,
    "dimension_seq_f1": 1,
    "sentiment_seq_f1": 1,
    "score": 0.2974137931034483,
    "train_loss": 0.6877699168718862,
    "val_loss": 8.782144799232483,
    "epoch_time": 137.28818941116333,
    "val_loss_va": 1.230080264210701,
    "train_loss_va": 0.14683240976904804
  },
  {
    "epoch": 62,
    "matrix_f1": 0.2980561555075594,
    "matrix_precision": 0.4726027397260274,
    "matrix_recall": 0.21766561514195584,
    "dimension_seq_f1": 1,
    "sentiment_seq_f1": 1,
    "score": 0.2980561555075594,
    "train_loss": 0.6762383708637116,
    "val_loss": 8.441396512985229,
    "epoch_time": 137.4737102985382,
    "val_loss_va": 1.2419023829698563,
    "train_loss_va": 0.15104934425660801
  },
  {
    "epoch": 63,
    "matrix_f1": 0.3073770491803278,
    "matrix_precision": 0.43859649122807015,
    "matrix_recall": 0.23659305993690852,
    "dimension_seq_f1": 1,
    "sentiment_seq_f1": 1,
    "score": 0.3073770491803278,
    "train_loss": 0.659581582477797,
    "val_loss": 9.176097462177276,
    "epoch_time": 138.38313674926758,
    "val_loss_va": 1.2592430639266967,
    "train_loss_va": 0.14631878578408428
  },
  {
    "epoch": 64,
    "matrix_f1": 0.30425963488843816,
    "matrix_precision": 0.42613636363636365,
    "matrix_recall": 0.23659305993690852,
    "dimension_seq_f1": 1,
    "sentiment_seq_f1": 1,
    "score": 0.30425963488843816,
    "train_loss": 0.6483065156015669,
    "val_loss": 8.936601629257202,
    "epoch_time": 139.04612183570862,
    "val_loss_va": 1.264625809788704,
    "train_loss_va": 0.15083241893181448
  },
  {
    "epoch": 65,
    "matrix_f1": 0.29914529914529914,
    "matrix_precision": 0.46357615894039733,
    "matrix_recall": 0.22082018927444794,
    "dimension_seq_f1": 1,
    "sentiment_seq_f1": 1,
    "score": 0.29914529914529914,
    "train_loss": 0.6295021607652964,
    "val_loss": 8.997635941505433,
    "epoch_time": 138.81636571884155,
    "val_loss_va": 1.233107048869133,
    "train_loss_va": 0.1460243354791865
  },
  {
    "epoch": 66,
    "matrix_f1": 0.2918454935622317,
    "matrix_precision": 0.4563758389261745,
    "matrix_recall": 0.21451104100946372,
    "dimension_seq_f1": 1,
    "sentiment_seq_f1": 1,
    "score": 0.2918454935622317,
    "train_loss": 0.6313762110973306,
    "val_loss": 9.434625380039215,
    "epoch_time": 138.49127626419067,
    "val_loss_va": 1.2732019186019898,
    "train_loss_va": 0.14434368958947147
  },
  {
    "epoch": 67,
    "matrix_f1": 0.30315789473684207,
    "matrix_precision": 0.45569620253164556,
    "matrix_recall": 0.22712933753943218,
    "dimension_seq_f1": 1,
    "sentiment_seq_f1": 1,
    "score": 0.30315789473684207,
    "train_loss": 0.6087041002158093,
    "val_loss": 9.179396736621857,
    "epoch_time": 138.48326015472412,
    "val_loss_va": 1.2191922104358672,
    "train_loss_va": 0.13853659292900528
  },
  {
    "epoch": 68,
    "matrix_f1": 0.29629629629629634,
    "matrix_precision": 0.4260355029585799,
    "matrix_recall": 0.22712933753943218,
    "dimension_seq_f1": 1,
    "sentiment_seq_f1": 1,
    "score": 0.29629629629629634,
    "train_loss": 0.5971628119574971,
    "val_loss": 8.916344311237335,
    "epoch_time": 138.85019993782043,
    "val_loss_va": 1.2705258536338806,
    "train_loss_va": 0.13822870932234282
  },
  {
    "epoch": 69,
    "matrix_f1": 0.2965931863727455,
    "matrix_precision": 0.4065934065934066,
    "matrix_recall": 0.2334384858044164,
    "dimension_seq_f1": 1,
    "sentiment_seq_f1": 1,
    "score": 0.2965931863727455,
    "train_loss": 0.5942517596427662,
    "val_loss": 9.127623918056488,
    "epoch_time": 138.55087447166443,
    "val_loss_va": 1.2997540146112443,
    "train_loss_va": 0.14289783724694274
  },
  {
    "epoch": 70,
    "matrix_f1": 0.28752642706131076,
    "matrix_precision": 0.4358974358974359,
    "matrix_recall": 0.21451104100946372,
    "dimension_seq_f1": 1,
    "sentiment_seq_f1": 1,
    "score": 0.28752642706131076,
    "train_loss": 0.5794144366082751,
    "val_loss": 9.355862050056457,
    "epoch_time": 138.48864650726318,
    "val_loss_va": 1.2711546641588212,
    "train_loss_va": 0.13797478062503762
  },
  {
    "epoch": 71,
    "matrix_f1": 0.2887473460721869,
    "matrix_precision": 0.44155844155844154,
    "matrix_recall": 0.21451104100946372,
    "dimension_seq_f1": 1,
    "sentiment_seq_f1": 1,
    "score": 0.2887473460721869,
    "train_loss": 0.5754556107107217,
    "val_loss": 9.432793571949006,
    "epoch_time": 138.36815857887268,
    "val_loss_va": 1.260087183713913,
    "train_loss_va": 0.13838523164596245
  },
  {
    "epoch": 72,
    "matrix_f1": 0.3022774327122153,
    "matrix_precision": 0.4397590361445783,
    "matrix_recall": 0.2302839116719243,
    "dimension_seq_f1": 1,
    "sentiment_seq_f1": 1,
    "score": 0.3022774327122153,
    "train_loss": 0.5608069233640195,
    "val_loss": 9.319294981956482,
    "epoch_time": 138.45949363708496,
    "val_loss_va": 1.2422516441345215,
    "train_loss_va": 0.13513383696219491
  },
  {
    "epoch": 73,
    "matrix_f1": 0.2967479674796748,
    "matrix_precision": 0.41714285714285715,
    "matrix_recall": 0.2302839116719243,
    "dimension_seq_f1": 1,
    "sentiment_seq_f1": 1,
    "score": 0.2967479674796748,
    "train_loss": 0.5515869012663654,
    "val_loss": 9.741362290382385,
    "epoch_time": 138.4213469028473,
    "val_loss_va": 1.320288165807724,
    "train_loss_va": 0.13024340829811076
  },
  {
    "epoch": 74,
    "matrix_f1": 0.3138075313807531,
    "matrix_precision": 0.4658385093167702,
    "matrix_recall": 0.23659305993690852,
    "dimension_seq_f1": 1,
    "sentiment_seq_f1": 1,
    "score": 0.3138075313807531,
    "train_loss": 0.5417611449664428,
    "val_loss": 9.654091522693633,
    "epoch_time": 138.39089035987854,
    "val_loss_va": 1.2625160735845566,
    "train_loss_va": 0.1318751988791741
  },
  {
    "epoch": 75,
    "matrix_f1": 0.3051546391752577,
    "matrix_precision": 0.44047619047619047,
    "matrix_recall": 0.2334384858044164,
    "dimension_seq_f1": 1,
    "sentiment_seq_f1": 1,
    "score": 0.3051546391752577,
    "train_loss": 0.5285719480891954,
    "val_loss": 9.903775169849396,
    "epoch_time": 138.61462354660034,
    "val_loss_va": 1.3090841048955917,
    "train_loss_va": 0.13187895543778258
  },
  {
    "epoch": 76,
    "matrix_f1": 0.31983805668016196,
    "matrix_precision": 0.4463276836158192,
    "matrix_recall": 0.24921135646687698,
    "dimension_seq_f1": 1,
    "sentiment_seq_f1": 1,
    "score": 0.31983805668016196,
    "train_loss": 0.5253386252264514,
    "val_loss": 9.973301594257356,
    "epoch_time": 138.64773631095886,
    "val_loss_va": 1.2805685180425643,
    "train_loss_va": 0.13106049593059133
  },
  {
    "epoch": 77,
    "matrix_f1": 0.3228346456692913,
    "matrix_precision": 0.4293193717277487,
    "matrix_recall": 0.2586750788643533,
    "dimension_seq_f1": 1,
    "sentiment_seq_f1": 1,
    "score": 0.3228346456692913,
    "train_loss": 0.5102990346853791,
    "val_loss": 9.551003744602204,
    "epoch_time": 138.79066514968872,
    "val_loss_va": 1.2681739348173142,
    "train_loss_va": 0.1311911324804998
  },
  {
    "epoch": 78,
    "matrix_f1": 0.3136456211812627,
    "matrix_precision": 0.4425287356321839,
    "matrix_recall": 0.24290220820189273,
    "dimension_seq_f1": 1,
    "sentiment_seq_f1": 1,
    "score": 0.3136456211812627,
    "train_loss": 0.5073637791248486,
    "val_loss": 9.869382507801056,
    "epoch_time": 138.6140480041504,
    "val_loss_va": 1.2753844475746154,
    "train_loss_va": 0.1291513592863896
  },
  {
    "epoch": 79,
    "matrix_f1": 0.3073684210526316,
    "matrix_precision": 0.4620253164556962,
    "matrix_recall": 0.2302839116719243,
    "dimension_seq_f1": 1,
    "sentiment_seq_f1": 1,
    "score": 0.3073684210526316,
    "train_loss": 0.4885764550180033,
    "val_loss": 10.187780222892762,
    "epoch_time": 138.82001900672913,
    "val_loss_va": 1.2706000143289566,
    "train_loss_va": 0.12492051989962442
  },
  {
    "epoch": 80,
    "matrix_f1": 0.32179226069246436,
    "matrix_precision": 0.4540229885057471,
    "matrix_recall": 0.24921135646687698,
    "dimension_seq_f1": 1,
    "sentiment_seq_f1": 1,
    "score": 0.32179226069246436,
    "train_loss": 0.4776535506549422,
    "val_loss": 10.25588040113449,
    "epoch_time": 138.96255946159363,
    "val_loss_va": 1.2326481866836547,
    "train_loss_va": 0.12282790248012636
  },
  {
    "epoch": 81,
    "matrix_f1": 0.3095238095238095,
    "matrix_precision": 0.41711229946524064,
    "matrix_recall": 0.24605678233438485,
    "dimension_seq_f1": 1,
    "sentiment_seq_f1": 1,
    "score": 0.3095238095238095,
    "train_loss": 0.4753729865572784,
    "val_loss": 10.00777895450592,
    "epoch_time": 138.52645087242126,
    "val_loss_va": 1.2672295200824737,
    "train_loss_va": 0.12498943054348494
  },
  {
    "epoch": 82,
    "matrix_f1": 0.30897703549060546,
    "matrix_precision": 0.4567901234567901,
    "matrix_recall": 0.2334384858044164,
    "dimension_seq_f1": 1,
    "sentiment_seq_f1": 1,
    "score": 0.30897703549060546,
    "train_loss": 0.46092213251032993,
    "val_loss": 10.414175486564636,
    "epoch_time": 138.59150862693787,
    "val_loss_va": 1.2998254042863846,
    "train_loss_va": 0.11931396601218967
  },
  {
    "epoch": 83,
    "matrix_f1": 0.3076923076923077,
    "matrix_precision": 0.4105263157894737,
    "matrix_recall": 0.24605678233438485,
    "dimension_seq_f1": 1,
    "sentiment_seq_f1": 1,
    "score": 0.3076923076923077,
    "train_loss": 0.45610767577329725,
    "val_loss": 10.426835117340088,
    "epoch_time": 138.684428691864,
    "val_loss_va": 1.2883342182636262,
    "train_loss_va": 0.12651172750451262
  },
  {
    "epoch": 84,
    "matrix_f1": 0.3176470588235294,
    "matrix_precision": 0.41968911917098445,
    "matrix_recall": 0.2555205047318612,
    "dimension_seq_f1": 1,
    "sentiment_seq_f1": 1,
    "score": 0.3176470588235294,
    "train_loss": 0.44565628500064874,
    "val_loss": 10.651384873390198,
    "epoch_time": 138.47869729995728,
    "val_loss_va": 1.2530521440505982,
    "train_loss_va": 0.12252737941714853
  },
  {
    "epoch": 85,
    "matrix_f1": 0.3107569721115538,
    "matrix_precision": 0.42162162162162165,
    "matrix_recall": 0.24605678233438485,
    "dimension_seq_f1": 1,
    "sentiment_seq_f1": 1,
    "score": 0.3107569721115538,
    "train_loss": 0.4419731404230189,
    "val_loss": 10.628445229530335,
    "epoch_time": 139.10850763320923,
    "val_loss_va": 1.2409674364328385,
    "train_loss_va": 0.11995094704923381
  },
  {
    "epoch": 86,
    "matrix_f1": 0.32391713747645945,
    "matrix_precision": 0.40186915887850466,
    "matrix_recall": 0.27129337539432175,
    "dimension_seq_f1": 1,
    "sentiment_seq_f1": 1,
    "score": 0.32391713747645945,
    "train_loss": 0.4253403048403013,
    "val_loss": 10.535006313323974,
    "epoch_time": 138.51596570014954,
    "val_loss_va": 1.2794018870592117,
    "train_loss_va": 0.11512233313242516
  },
  {
    "epoch": 87,
    "matrix_f1": 0.32295719844357973,
    "matrix_precision": 0.4213197969543147,
    "matrix_recall": 0.2618296529968454,
    "dimension_seq_f1": 1,
    "sentiment_seq_f1": 1,
    "score": 0.32295719844357973,
    "train_loss": 0.41686795749523337,
    "val_loss": 10.660773837566376,
    "epoch_time": 138.08235263824463,
    "val_loss_va": 1.2773744767904283,
    "train_loss_va": 0.11741246201529353
  },
  {
    "epoch": 88,
    "matrix_f1": 0.3025540275049116,
    "matrix_precision": 0.4010416666666667,
    "matrix_recall": 0.24290220820189273,
    "dimension_seq_f1": 1,
    "sentiment_seq_f1": 1,
    "score": 0.3025540275049116,
    "train_loss": 0.4122612137252408,
    "val_loss": 11.18290314912796,
    "epoch_time": 138.04655003547668,
    "val_loss_va": 1.2486308866739273,
    "train_loss_va": 0.12094305330198313
  },
  {
    "epoch": 89,
    "matrix_f1": 0.3300589390962672,
    "matrix_precision": 0.4375,
    "matrix_recall": 0.26498422712933756,
    "dimension_seq_f1": 1,
    "sentiment_seq_f1": 1,
    "score": 0.3300589390962672,
    "train_loss": 0.40438734158741946,
    "val_loss": 11.245052323341369,
    "epoch_time": 137.6227467060089,
    "val_loss_va": 1.2530568301677705,
    "train_loss_va": 0.11853458542994592
  },
  {
    "epoch": 90,
    "matrix_f1": 0.31517509727626464,
    "matrix_precision": 0.41116751269035534,
    "matrix_recall": 0.2555205047318612,
    "dimension_seq_f1": 1,
    "sentiment_seq_f1": 1,
    "score": 0.31517509727626464,
    "train_loss": 0.3976913152721375,
    "val_loss": 11.176454617977143,
    "epoch_time": 137.45127868652344,
    "val_loss_va": 1.2825766360759736,
    "train_loss_va": 0.11588228180715714
  },
  {
    "epoch": 91,
    "matrix_f1": 0.31213872832369943,
    "matrix_precision": 0.400990099009901,
    "matrix_recall": 0.2555205047318612,
    "dimension_seq_f1": 1,
    "sentiment_seq_f1": 1,
    "score": 0.31213872832369943,
    "train_loss": 0.3916137745974986,
    "val_loss": 11.139604079723359,
    "epoch_time": 137.9164958000183,
    "val_loss_va": 1.2653681653738023,
    "train_loss_va": 0.11576533829930427
  },
  {
    "epoch": 92,
    "matrix_f1": 0.31578947368421056,
    "matrix_precision": 0.413265306122449,
    "matrix_recall": 0.2555205047318612,
    "dimension_seq_f1": 1,
    "sentiment_seq_f1": 1,
    "score": 0.31578947368421056,
    "train_loss": 0.38130753195430567,
    "val_loss": 11.667189507484435,
    "epoch_time": 137.4810791015625,
    "val_loss_va": 1.2567851954698563,
    "train_loss_va": 0.11276638577852154
  },
  {
    "epoch": 93,
    "matrix_f1": 0.3204633204633205,
    "matrix_precision": 0.4129353233830846,
    "matrix_recall": 0.2618296529968454,
    "dimension_seq_f1": 1,
    "sentiment_seq_f1": 1,
    "score": 0.3204633204633205,
    "train_loss": 0.37458128475888436,
    "val_loss": 11.08989697933197,
    "epoch_time": 138.10161566734314,
    "val_loss_va": 1.2522186988592148,
    "train_loss_va": 0.11012743809191881
  },
  {
    "epoch": 94,
    "matrix_f1": 0.3120300751879699,
    "matrix_precision": 0.386046511627907,
    "matrix_recall": 0.2618296529968454,
    "dimension_seq_f1": 1,
    "sentiment_seq_f1": 1,
    "score": 0.3120300751879699,
    "train_loss": 0.36841367102128486,
    "val_loss": 11.346120665073395,
    "epoch_time": 137.7012369632721,
    "val_loss_va": 1.2130503845214844,
    "train_loss_va": 0.11251807657104275
  },
  {
    "epoch": 95,
    "matrix_f1": 0.30039525691699603,
    "matrix_precision": 0.4021164021164021,
    "matrix_recall": 0.23974763406940064,
    "dimension_seq_f1": 1,
    "sentiment_seq_f1": 1,
    "score": 0.30039525691699603,
    "train_loss": 0.36161234635965744,
    "val_loss": 11.65660385608673,
    "epoch_time": 138.12494206428528,
    "val_loss_va": 1.2201595902442932,
    "train_loss_va": 0.10951958591862417
  },
  {
    "epoch": 96,
    "matrix_f1": 0.32245681381957775,
    "matrix_precision": 0.4117647058823529,
    "matrix_recall": 0.26498422712933756,
    "dimension_seq_f1": 1,
    "sentiment_seq_f1": 1,
    "score": 0.32245681381957775,
    "train_loss": 0.35195568550315937,
    "val_loss": 11.980835721492767,
    "epoch_time": 137.96386218070984,
    "val_loss_va": 1.271792587041855,
    "train_loss_va": 0.10846285151648569
  },
  {
    "epoch": 97,
    "matrix_f1": 0.308300395256917,
    "matrix_precision": 0.4126984126984127,
    "matrix_recall": 0.24605678233438485,
    "dimension_seq_f1": 1,
    "sentiment_seq_f1": 1,
    "score": 0.308300395256917,
    "train_loss": 0.3436702686189231,
    "val_loss": 11.701009395122528,
    "epoch_time": 137.73400688171387,
    "val_loss_va": 1.203399556875229,
    "train_loss_va": 0.11000802047492185
  },
  {
    "epoch": 98,
    "matrix_f1": 0.31261770244821097,
    "matrix_precision": 0.3878504672897196,
    "matrix_recall": 0.2618296529968454,
    "dimension_seq_f1": 1,
    "sentiment_seq_f1": 1,
    "score": 0.31261770244821097,
    "train_loss": 0.34545725407088,
    "val_loss": 11.449914121627808,
    "epoch_time": 137.63334155082703,
    "val_loss_va": 1.2597558772563935,
    "train_loss_va": 0.1107990637099895
  },
  {
    "epoch": 99,
    "matrix_f1": 0.3147792706333973,
    "matrix_precision": 0.4019607843137255,
    "matrix_recall": 0.2586750788643533,
    "dimension_seq_f1": 1,
    "sentiment_seq_f1": 1,
    "score": 0.3147792706333973,
    "train_loss": 0.332274118612015,
    "val_loss": 11.768202004432679,
    "epoch_time": 137.4062807559967,
    "val_loss_va": 1.2618303447961807,
    "train_loss_va": 0.10606426085821619
  },
  {
    "epoch": 100,
    "matrix_f1": 0.3193612774451098,
    "matrix_precision": 0.43478260869565216,
    "matrix_recall": 0.25236593059936907,
    "dimension_seq_f1": 1,
    "sentiment_seq_f1": 1,
    "score": 0.3193612774451098,
    "train_loss": 0.3256706310448925,
    "val_loss": 12.357027537822724,
    "epoch_time": 137.33664274215698,
    "val_loss_va": 1.2832408887147904,
    "train_loss_va": 0.10655745083577675
  },
  {
    "epoch": 101,
    "matrix_f1": 0.3165735567970205,
    "matrix_precision": 0.38636363636363635,
    "matrix_recall": 0.26813880126182965,
    "dimension_seq_f1": 1,
    "sentiment_seq_f1": 1,
    "score": 0.3165735567970205,
    "train_loss": 0.3177111624037231,
    "val_loss": 11.951653196811677,
    "epoch_time": 137.68822765350342,
    "val_loss_va": 1.275474010705948,
    "train_loss_va": 0.10351724946054322
  },
  {
    "epoch": 102,
    "matrix_f1": 0.3217054263565891,
    "matrix_precision": 0.41708542713567837,
    "matrix_recall": 0.2618296529968454,
    "dimension_seq_f1": 1,
    "sentiment_seq_f1": 1,
    "score": 0.3217054263565891,
    "train_loss": 0.3163959850265596,
    "val_loss": 12.25481909751892,
    "epoch_time": 137.86041808128357,
    "val_loss_va": 1.2612966895103455,
    "train_loss_va": 0.10707448065779936
  },
  {
    "epoch": 103,
    "matrix_f1": 0.3203125,
    "matrix_precision": 0.4205128205128205,
    "matrix_recall": 0.2586750788643533,
    "dimension_seq_f1": 1,
    "sentiment_seq_f1": 1,
    "score": 0.3203125,
    "train_loss": 0.3098061812824046,
    "val_loss": 12.490045645236968,
    "epoch_time": 137.37919926643372,
    "val_loss_va": 1.2570344465970993,
    "train_loss_va": 0.10259821639104698
  },
  {
    "epoch": 104,
    "matrix_f1": 0.30739299610894943,
    "matrix_precision": 0.4010152284263959,
    "matrix_recall": 0.24921135646687698,
    "dimension_seq_f1": 1,
    "sentiment_seq_f1": 1,
    "score": 0.30739299610894943,
    "train_loss": 0.30354446161746745,
    "val_loss": 12.09618232011795,
    "epoch_time": 137.46720337867737,
    "val_loss_va": 1.315626123547554,
    "train_loss_va": 0.10202925376478908
  },
  {
    "epoch": 105,
    "matrix_f1": 0.3352165725047081,
    "matrix_precision": 0.4158878504672897,
    "matrix_recall": 0.2807570977917981,
    "dimension_seq_f1": 1,
    "sentiment_seq_f1": 1,
    "score": 0.3352165725047081,
    "train_loss": 0.3004839122057751,
    "val_loss": 12.509359517097472,
    "epoch_time": 137.63013982772827,
    "val_loss_va": 1.2613614588975905,
    "train_loss_va": 0.10312863511798338
  },
  {
    "epoch": 106,
    "matrix_f1": 0.3114446529080675,
    "matrix_precision": 0.38425925925925924,
    "matrix_recall": 0.2618296529968454,
    "dimension_seq_f1": 1,
    "sentiment_seq_f1": 1,
    "score": 0.3114446529080675,
    "train_loss": 0.2924763891403586,
    "val_loss": 12.336447789669037,
    "epoch_time": 137.50448727607727,
    "val_loss_va": 1.227778639793396,
    "train_loss_va": 0.104059786975413
  },
  {
    "epoch": 107,
    "matrix_f1": 0.3178294573643411,
    "matrix_precision": 0.4120603015075377,
    "matrix_recall": 0.2586750788643533,
    "dimension_seq_f1": 1,
    "sentiment_seq_f1": 1,
    "score": 0.3178294573643411,
    "train_loss": 0.2830032838382361,
    "val_loss": 12.551005618572235,
    "epoch_time": 137.41461372375488,
    "val_loss_va": 1.254569999575615,
    "train_loss_va": 0.09949903362142735
  },
  {
    "epoch": 108,
    "matrix_f1": 0.30711610486891383,
    "matrix_precision": 0.3778801843317972,
    "matrix_recall": 0.2586750788643533,
    "dimension_seq_f1": 1,
    "sentiment_seq_f1": 1,
    "score": 0.30711610486891383,
    "train_loss": 0.2801010946380349,
    "val_loss": 12.750356335639953,
    "epoch_time": 137.5582344532013,
    "val_loss_va": 1.2503468483686446,
    "train_loss_va": 0.09986892108777146
  },
  {
    "epoch": 109,
    "matrix_f1": 0.3192307692307692,
    "matrix_precision": 0.4088669950738916,
    "matrix_recall": 0.2618296529968454,
    "dimension_seq_f1": 1,
    "sentiment_seq_f1": 1,
    "score": 0.3192307692307692,
    "train_loss": 0.27963515211324463,
    "val_loss": 12.730429651737213,
    "epoch_time": 137.93367433547974,
    "val_loss_va": 1.2630904829502105,
    "train_loss_va": 0.09900915195344709
  },
  {
    "epoch": 110,
    "matrix_f1": 0.3099630996309963,
    "matrix_precision": 0.37333333333333335,
    "matrix_recall": 0.26498422712933756,
    "dimension_seq_f1": 1,
    "sentiment_seq_f1": 1,
    "score": 0.3099630996309963,
    "train_loss": 0.26662730185591027,
    "val_loss": 12.469711961746215,
    "epoch_time": 138.06113386154175,
    "val_loss_va": 1.2278918200731277,
    "train_loss_va": 0.0953779260594109
  },
  {
    "epoch": 111,
    "matrix_f1": 0.32432432432432434,
    "matrix_precision": 0.37815126050420167,
    "matrix_recall": 0.28391167192429023,
    "dimension_seq_f1": 1,
    "sentiment_seq_f1": 1,
    "score": 0.32432432432432434,
    "train_loss": 0.2633808667883935,
    "val_loss": 12.892847497463226,
    "epoch_time": 137.94078183174133,
    "val_loss_va": 1.2630938595533372,
    "train_loss_va": 0.09813849154998702
  },
  {
    "epoch": 112,
    "matrix_f1": 0.31775700934579443,
    "matrix_precision": 0.38990825688073394,
    "matrix_recall": 0.26813880126182965,
    "dimension_seq_f1": 1,
    "sentiment_seq_f1": 1,
    "score": 0.31775700934579443,
    "train_loss": 0.2635407286729952,
    "val_loss": 12.674104363918305,
    "epoch_time": 137.76988673210144,
    "val_loss_va": 1.2449754917621612,
    "train_loss_va": 0.10025823969573104
  },
  {
    "epoch": 113,
    "matrix_f1": 0.3193916349809886,
    "matrix_precision": 0.4019138755980861,
    "matrix_recall": 0.26498422712933756,
    "dimension_seq_f1": 1,
    "sentiment_seq_f1": 1,
    "score": 0.3193916349809886,
    "train_loss": 0.25718588010664806,
    "val_loss": 13.272625067234038,
    "epoch_time": 137.63319540023804,
    "val_loss_va": 1.2901193684339523,
    "train_loss_va": 0.0987596364574867
  },
  {
    "epoch": 114,
    "matrix_f1": 0.3222222222222222,
    "matrix_precision": 0.3901345291479821,
    "matrix_recall": 0.2744479495268139,
    "dimension_seq_f1": 1,
    "sentiment_seq_f1": 1,
    "score": 0.3222222222222222,
    "train_loss": 0.2522081579515844,
    "val_loss": 13.142061660289764,
    "epoch_time": 137.59397292137146,
    "val_loss_va": 1.29555477976799,
    "train_loss_va": 0.09804543636563774
  },
  {
    "epoch": 115,
    "matrix_f1": 0.31379962192816635,
    "matrix_precision": 0.3915094339622642,
    "matrix_recall": 0.2618296529968454,
    "dimension_seq_f1": 1,
    "sentiment_seq_f1": 1,
    "score": 0.31379962192816635,
    "train_loss": 0.2506026496600736,
    "val_loss": 13.519103202819824,
    "epoch_time": 137.5961651802063,
    "val_loss_va": 1.3053897327184678,
    "train_loss_va": 0.09624703115280041
  },
  {
    "epoch": 116,
    "matrix_f1": 0.316793893129771,
    "matrix_precision": 0.40096618357487923,
    "matrix_recall": 0.2618296529968454,
    "dimension_seq_f1": 1,
    "sentiment_seq_f1": 1,
    "score": 0.316793893129771,
    "train_loss": 0.24230562892977342,
    "val_loss": 13.26610566854477,
    "epoch_time": 137.52086901664734,
    "val_loss_va": 1.2429822885990143,
    "train_loss_va": 0.09513562246499048
  },
  {
    "epoch": 117,
    "matrix_f1": 0.3187855787476281,
    "matrix_precision": 0.4,
    "matrix_recall": 0.26498422712933756,
    "dimension_seq_f1": 1,
    "sentiment_seq_f1": 1,
    "score": 0.3187855787476281,
    "train_loss": 0.23682644173605286,
    "val_loss": 13.962471594810486,
    "epoch_time": 137.81997752189636,
    "val_loss_va": 1.269673117995262,
    "train_loss_va": 0.09430367889804026
  },
  {
    "epoch": 118,
    "matrix_f1": 0.3171641791044776,
    "matrix_precision": 0.3881278538812785,
    "matrix_recall": 0.26813880126182965,
    "dimension_seq_f1": 1,
    "sentiment_seq_f1": 1,
    "score": 0.3171641791044776,
    "train_loss": 0.2318759277020604,
    "val_loss": 13.387477335929871,
    "epoch_time": 138.0891444683075,
    "val_loss_va": 1.259458235502243,
    "train_loss_va": 0.09409004785449512
  },
  {
    "epoch": 119,
    "matrix_f1": 0.32897196261682243,
    "matrix_precision": 0.4036697247706422,
    "matrix_recall": 0.277602523659306,
    "dimension_seq_f1": 1,
    "sentiment_seq_f1": 1,
    "score": 0.32897196261682243,
    "train_loss": 0.23090079939495534,
    "val_loss": 13.65914973974228,
    "epoch_time": 137.6802945137024,
    "val_loss_va": 1.2685054814815522,
    "train_loss_va": 0.09382423977399569
  },
  {
    "epoch": 120,
    "matrix_f1": 0.3169811320754717,
    "matrix_precision": 0.39436619718309857,
    "matrix_recall": 0.26498422712933756,
    "dimension_seq_f1": 1,
    "sentiment_seq_f1": 1,
    "score": 0.3169811320754717,
    "train_loss": 0.2298400775192194,
    "val_loss": 13.878961291313171,
    "epoch_time": 137.56822443008423,
    "val_loss_va": 1.2622388762235641,
    "train_loss_va": 0.09234494276955299
  },
  {
    "epoch": 121,
    "matrix_f1": 0.2988505747126437,
    "matrix_precision": 0.3804878048780488,
    "matrix_recall": 0.24605678233438485,
    "dimension_seq_f1": 1,
    "sentiment_seq_f1": 1,
    "score": 0.2988505747126437,
    "train_loss": 0.2232651191181389,
    "val_loss": 14.28546522140503,
    "epoch_time": 137.5700719356537,
    "val_loss_va": 1.2753441715240479,
    "train_loss_va": 0.09074702055693419
  },
  {
    "epoch": 122,
    "matrix_f1": 0.32902033271719033,
    "matrix_precision": 0.39732142857142855,
    "matrix_recall": 0.2807570977917981,
    "dimension_seq_f1": 1,
    "sentiment_seq_f1": 1,
    "score": 0.32902033271719033,
    "train_loss": 0.2146517820711137,
    "val_loss": 14.172043476104736,
    "epoch_time": 137.44351434707642,
    "val_loss_va": 1.2954485893249512,
    "train_loss_va": 0.09160674557225071
  },
  {
    "epoch": 123,
    "matrix_f1": 0.31460674157303375,
    "matrix_precision": 0.3870967741935484,
    "matrix_recall": 0.26498422712933756,
    "dimension_seq_f1": 1,
    "sentiment_seq_f1": 1,
    "score": 0.31460674157303375,
    "train_loss": 0.2145505549662159,
    "val_loss": 13.811341817378997,
    "epoch_time": 136.76304650306702,
    "val_loss_va": 1.2704641544818878,
    "train_loss_va": 0.08876157025747199
  },
  {
    "epoch": 124,
    "matrix_f1": 0.33648393194706994,
    "matrix_precision": 0.419811320754717,
    "matrix_recall": 0.2807570977917981,
    "dimension_seq_f1": 1,
    "sentiment_seq_f1": 1,
    "score": 0.33648393194706994,
    "train_loss": 0.2079848193538844,
    "val_loss": 14.060371029376984,
    "epoch_time": 135.79518222808838,
    "val_loss_va": 1.248980917930603,
    "train_loss_va": 0.08706957057037988
  },
  {
    "epoch": 125,
    "matrix_f1": 0.3067961165048544,
    "matrix_precision": 0.398989898989899,
    "matrix_recall": 0.24921135646687698,
    "dimension_seq_f1": 1,
    "sentiment_seq_f1": 1,
    "score": 0.3067961165048544,
    "train_loss": 0.21135673353172496,
    "val_loss": 14.160153830051422,
    "epoch_time": 136.02878260612488,
    "val_loss_va": 1.244081734418869,
    "train_loss_va": 0.08890743038394983
  },
  {
    "epoch": 126,
    "matrix_f1": 0.32391713747645945,
    "matrix_precision": 0.40186915887850466,
    "matrix_recall": 0.27129337539432175,
    "dimension_seq_f1": 1,
    "sentiment_seq_f1": 1,
    "score": 0.32391713747645945,
    "train_loss": 0.2014305323821157,
    "val_loss": 14.014433741569519,
    "epoch_time": 136.09152722358704,
    "val_loss_va": 1.2744870805740356,
    "train_loss_va": 0.08706305283592453
  },
  {
    "epoch": 127,
    "matrix_f1": 0.33451957295373663,
    "matrix_precision": 0.3836734693877551,
    "matrix_recall": 0.29652996845425866,
    "dimension_seq_f1": 1,
    "sentiment_seq_f1": 1,
    "score": 0.33451957295373663,
    "train_loss": 0.1996489813052286,
    "val_loss": 13.623873772621154,
    "epoch_time": 135.99482250213623,
    "val_loss_va": 1.2679962235689164,
    "train_loss_va": 0.08575506264323751
  },
  {
    "epoch": 128,
    "matrix_f1": 0.3102803738317757,
    "matrix_precision": 0.38073394495412843,
    "matrix_recall": 0.2618296529968454,
    "dimension_seq_f1": 1,
    "sentiment_seq_f1": 1,
    "score": 0.3102803738317757,
    "train_loss": 0.19525649203161202,
    "val_loss": 14.08937005519867,
    "epoch_time": 135.82649636268616,
    "val_loss_va": 1.2339477777481078,
    "train_loss_va": 0.08628403742352575
  },
  {
    "epoch": 129,
    "matrix_f1": 0.3135755258126195,
    "matrix_precision": 0.39805825242718446,
    "matrix_recall": 0.2586750788643533,
    "dimension_seq_f1": 1,
    "sentiment_seq_f1": 1,
    "score": 0.3135755258126195,
    "train_loss": 0.19215918786940736,
    "val_loss": 14.179030556678772,
    "epoch_time": 135.89936327934265,
    "val_loss_va": 1.2398396027088165,
    "train_loss_va": 0.08592466739764011
  },
  {
    "epoch": 130,
    "matrix_f1": 0.3289224952741021,
    "matrix_precision": 0.41037735849056606,
    "matrix_recall": 0.2744479495268139,
    "dimension_seq_f1": 1,
    "sentiment_seq_f1": 1,
    "score": 0.3289224952741021,
    "train_loss": 0.19524243745634787,
    "val_loss": 14.48559607744217,
    "epoch_time": 135.9232096672058,
    "val_loss_va": 1.235077137351036,
    "train_loss_va": 0.0879081986452452
  },
  {
    "epoch": 131,
    "matrix_f1": 0.31792975970425136,
    "matrix_precision": 0.38392857142857145,
    "matrix_recall": 0.27129337539432175,
    "dimension_seq_f1": 1,
    "sentiment_seq_f1": 1,
    "score": 0.31792975970425136,
    "train_loss": 0.18532740882615228,
    "val_loss": 15.544533052444457,
    "epoch_time": 136.15436792373657,
    "val_loss_va": 1.2231403464078903,
    "train_loss_va": 0.08347774881200538
  },
  {
    "epoch": 132,
    "matrix_f1": 0.32941176470588235,
    "matrix_precision": 0.43523316062176165,
    "matrix_recall": 0.26498422712933756,
    "dimension_seq_f1": 1,
    "sentiment_seq_f1": 1,
    "score": 0.32941176470588235,
    "train_loss": 0.18421238431957448,
    "val_loss": 14.654055795669557,
    "epoch_time": 136.16643381118774,
    "val_loss_va": 1.2218621581792832,
    "train_loss_va": 0.0855328572084131
  },
  {
    "epoch": 133,
    "matrix_f1": 0.31619047619047613,
    "matrix_precision": 0.39903846153846156,
    "matrix_recall": 0.2618296529968454,
    "dimension_seq_f1": 1,
    "sentiment_seq_f1": 1,
    "score": 0.31619047619047613,
    "train_loss": 0.1850941865444476,
    "val_loss": 14.67754332780838,
    "epoch_time": 135.89398002624512,
    "val_loss_va": 1.2011337989568711,
    "train_loss_va": 0.08617425344471287
  },
  {
    "epoch": 134,
    "matrix_f1": 0.3277467411545624,
    "matrix_precision": 0.4,
    "matrix_recall": 0.277602523659306,
    "dimension_seq_f1": 1,
    "sentiment_seq_f1": 1,
    "score": 0.3277467411545624,
    "train_loss": 0.17681935536871657,
    "val_loss": 14.928199751377106,
    "epoch_time": 136.0057716369629,
    "val_loss_va": 1.2578895831108092,
    "train_loss_va": 0.08281606487140161
  },
  {
    "epoch": 135,
    "matrix_f1": 0.33079847908745247,
    "matrix_precision": 0.41626794258373206,
    "matrix_recall": 0.2744479495268139,
    "dimension_seq_f1": 1,
    "sentiment_seq_f1": 1,
    "score": 0.33079847908745247,
    "train_loss": 0.16527807561751964,
    "val_loss": 14.751776571273803,
    "epoch_time": 136.01508712768555,
    "val_loss_va": 1.2229155898094177,
    "train_loss_va": 0.08316574258212515
  },
  {
    "epoch": 136,
    "matrix_f1": 0.3233082706766917,
    "matrix_precision": 0.4,
    "matrix_recall": 0.27129337539432175,
    "dimension_seq_f1": 1,
    "sentiment_seq_f1": 1,
    "score": 0.3233082706766917,
    "train_loss": 0.17105864886088448,
    "val_loss": 15.097199761867524,
    "epoch_time": 135.9556760787964,
    "val_loss_va": 1.2583170962333678,
    "train_loss_va": 0.08126674068797383
  },
  {
    "epoch": 137,
    "matrix_f1": 0.31238095238095237,
    "matrix_precision": 0.3942307692307692,
    "matrix_recall": 0.2586750788643533,
    "dimension_seq_f1": 1,
    "sentiment_seq_f1": 1,
    "score": 0.31238095238095237,
    "train_loss": 0.16565944161905857,
    "val_loss": 15.652020440101623,
    "epoch_time": 135.81703567504883,
    "val_loss_va": 1.3016425451636315,
    "train_loss_va": 0.08306844601996236
  },
  {
    "epoch": 138,
    "matrix_f1": 0.3333333333333333,
    "matrix_precision": 0.40358744394618834,
    "matrix_recall": 0.28391167192429023,
    "dimension_seq_f1": 1,
    "sentiment_seq_f1": 1,
    "score": 0.3333333333333333,
    "train_loss": 0.16625972360672323,
    "val_loss": 15.083185319900513,
    "epoch_time": 135.89162755012512,
    "val_loss_va": 1.2802482861280442,
    "train_loss_va": 0.08304745405345745
  },
  {
    "epoch": 139,
    "matrix_f1": 0.32,
    "matrix_precision": 0.40384615384615385,
    "matrix_recall": 0.26498422712933756,
    "dimension_seq_f1": 1,
    "sentiment_seq_f1": 1,
    "score": 0.32,
    "train_loss": 0.16415326650436307,
    "val_loss": 15.352486886978149,
    "epoch_time": 135.95226454734802,
    "val_loss_va": 1.259589009284973,
    "train_loss_va": 0.08398354585054929
  },
  {
    "epoch": 140,
    "matrix_f1": 0.3285198555956679,
    "matrix_precision": 0.38396624472573837,
    "matrix_recall": 0.2870662460567823,
    "dimension_seq_f1": 1,
    "sentiment_seq_f1": 1,
    "score": 0.3285198555956679,
    "train_loss": 0.16456011156857717,
    "val_loss": 15.081909599304199,
    "epoch_time": 135.88258957862854,
    "val_loss_va": 1.255003544986248,
    "train_loss_va": 0.08123849850409354
  },
  {
    "epoch": 141,
    "matrix_f1": 0.3114446529080675,
    "matrix_precision": 0.38425925925925924,
    "matrix_recall": 0.2618296529968454,
    "dimension_seq_f1": 1,
    "sentiment_seq_f1": 1,
    "score": 0.3114446529080675,
    "train_loss": 0.1600849827051426,
    "val_loss": 15.87415128469467,
    "epoch_time": 135.2027108669281,
    "val_loss_va": 1.2607336458563805,
    "train_loss_va": 0.08225826188187106
  },
  {
    "epoch": 142,
    "matrix_f1": 0.31460674157303375,
    "matrix_precision": 0.3870967741935484,
    "matrix_recall": 0.26498422712933756,
    "dimension_seq_f1": 1,
    "sentiment_seq_f1": 1,
    "score": 0.31460674157303375,
    "train_loss": 0.1540577045995541,
    "val_loss": 15.379512929916382,
    "epoch_time": 135.59025073051453,
    "val_loss_va": 1.2788866829872132,
    "train_loss_va": 0.07802340082396499
  },
  {
    "epoch": 143,
    "matrix_f1": 0.31034482758620685,
    "matrix_precision": 0.3951219512195122,
    "matrix_recall": 0.2555205047318612,
    "dimension_seq_f1": 1,
    "sentiment_seq_f1": 1,
    "score": 0.31034482758620685,
    "train_loss": 0.15145442742302326,
    "val_loss": 15.86216742515564,
    "epoch_time": 135.5732936859131,
    "val_loss_va": 1.2832437771558762,
    "train_loss_va": 0.08094135478734824
  },
  {
    "epoch": 144,
    "matrix_f1": 0.3155963302752294,
    "matrix_precision": 0.37719298245614036,
    "matrix_recall": 0.27129337539432175,
    "dimension_seq_f1": 1,
    "sentiment_seq_f1": 1,
    "score": 0.3155963302752294,
    "train_loss": 0.15205282307941909,
    "val_loss": 15.169012129306793,
    "epoch_time": 135.63692474365234,
    "val_loss_va": 1.2596226292848587,
    "train_loss_va": 0.08178389724206922
  }
]